livekit/plugins/sub200/README.md
livekit/plugins/sub200/__init__.py
livekit/plugins/sub200/log.py
livekit/plugins/sub200/py.typed
livekit/plugins/sub200/tts.py
livekit/plugins/sub200/version.py
livekit_plugins_sub200-0.1.1.dist-info/METADATA
livekit_plugins_sub200-0.1.1.dist-info/WHEEL
livekit_plugins_sub200-0.1.1.dist-info/RECORD
