Metadata-Version: 2.4
Name: livekit-plugins-sub200
Version: 0.1.1
Summary: Agent Framework plugin for Sub200 text-to-speech.
Project-URL: Documentation, https://docs.livekit.io
Project-URL: Website, https://livekit.io/
Project-URL: Source, https://github.com/livekit/agents
Author-email: LiveKit <hello@livekit.io>
License-Expression: Apache-2.0
Keywords: audio,livekit,realtime,sub200,tts,video,webrtc
Classifier: Intended Audience :: Developers
Classifier: License :: OSI Approved :: Apache Software License
Classifier: Programming Language :: Python :: 3
Classifier: Programming Language :: Python :: 3 :: Only
Classifier: Programming Language :: Python :: 3.9
Classifier: Programming Language :: Python :: 3.10
Classifier: Topic :: Multimedia :: Sound/Audio
Classifier: Topic :: Multimedia :: Video
Classifier: Topic :: Scientific/Engineering :: Artificial Intelligence
Requires-Python: >=3.9.0
Requires-Dist: aiohttp>=3.10
Requires-Dist: livekit-agents[codecs]>=1.3.9
